<annotation>
	<folder>Pizza</folder>
	<filename>Pizza-Train (115).jpeg</filename>
	<path>C:\Users\Tokiru\Documents\College Files\4TH YEAR 1ST TERM\THESIS2\FoodDetection\Tensorflow\workspace\images\train\Pizza\Pizza-Train (115).jpeg</path>
	<source>
		<database>Unknown</database>
	</source>
	<size>
		<width>311</width>
		<height>162</height>
		<depth>3</depth>
	</size>
	<segmented>0</segmented>
	<object>
		<name>Pizza</name>
		<pose>Unspecified</pose>
		<truncated>0</truncated>
		<difficult>0</difficult>
		<bndbox>
			<xmin>50</xmin>
			<ymin>92</ymin>
			<xmax>104</xmax>
			<ymax>155</ymax>
		</bndbox>
	</object>
	<object>
		<name>Pizza</name>
		<pose>Unspecified</pose>
		<truncated>0</truncated>
		<difficult>0</difficult>
		<bndbox>
			<xmin>102</xmin>
			<ymin>44</ymin>
			<xmax>150</xmax>
			<ymax>86</ymax>
		</bndbox>
	</object>
	<object>
		<name>Pizza</name>
		<pose>Unspecified</pose>
		<truncated>0</truncated>
		<difficult>0</difficult>
		<bndbox>
			<xmin>159</xmin>
			<ymin>41</ymin>
			<xmax>207</xmax>
			<ymax>84</ymax>
		</bndbox>
	</object>
	<object>
		<name>Pizza</name>
		<pose>Unspecified</pose>
		<truncated>0</truncated>
		<difficult>0</difficult>
		<bndbox>
			<xmin>218</xmin>
			<ymin>66</ymin>
			<xmax>259</xmax>
			<ymax>107</ymax>
		</bndbox>
	</object>
	<object>
		<name>Pizza</name>
		<pose>Unspecified</pose>
		<truncated>0</truncated>
		<difficult>0</difficult>
		<bndbox>
			<xmin>143</xmin>
			<ymin>100</ymin>
			<xmax>195</xmax>
			<ymax>149</ymax>
		</bndbox>
	</object>
</annotation>
